teimpy/__init__.py
teimpy/drawer.py
teimpy/impl/__init__.py
teimpy/impl/base.py
teimpy/impl/block.py
teimpy/impl/braille.py
teimpy/impl/iterm2_inline_image.py
teimpy/impl/sixel.py
teimpy/impl/util.py
teimpy/shape.py
teimpy-0.0.3.dist-info/LICENSE
teimpy-0.0.3.dist-info/WHEEL
teimpy-0.0.3.dist-info/METADATA
teimpy-0.0.3.dist-info/RECORD
