Metadata-Version: 2.1
Name: teimpy
Version: 0.0.3
Summary: Python libray for displaying images on terminal
Home-page: https://github.com/ar90n/teimpy
License: MIT
Keywords: sixel,terminal,graphics
Author: Masahiro Wada
Author-email: argon.argon.argon@gmail.com
Requires-Python: >=3.6,<4.0
Classifier: License :: OSI Approved :: MIT License
Classifier: Programming Language :: Python :: 3
Classifier: Programming Language :: Python :: 3.6
Classifier: Programming Language :: Python :: 3.7
Classifier: Programming Language :: Python :: 3.8
Requires-Dist: numpy (>=1.16.0,<2.0.0)
Requires-Dist: pillow (>=6.0.0,<7.0.0)
Requires-Dist: pysixel (>=0.1.11,<0.2.0)
Project-URL: Repository, https://github.com/ar90n/teimpy
